no idea/Term_Project/Term_Project.srcs/sources_1/new/hockey.v
`timescale 1ns / 1ps
//////////////////////////////////////////////////////////////////////////////////
// Company: 
// Engineer: 
// 
// Create Date: 01/01/2024 11:12:09 PM
// Design Name: 
// Module Name: hockey
// Project Name: 
// Target Devices: 
// Tool Versions: 
// Description: 
// 
// Dependencies: 
// 
// Revision:
// Revision 0.01 - File Created
// Additional Comments:
// 
//////////////////////////////////////////////////////////////////////////////////


module hockey(

input clk,
input rst,

input BTN_A,
input BTN_B,

input [1:0] DIR_A,
input [1:0] DIR_B,

input [2:0] Y_in_A,
input [2:0] Y_in_B,

/*output reg LEDA,
output reg LEDB,
output reg [4:0] LEDX,

output reg [6:0] SSD7,
output reg [6:0] SSD6,
output reg [6:0] SSD5,
output reg [6:0] SSD4, 
output reg [6:0] SSD3,
output reg [6:0] SSD2,
output reg [6:0] SSD1,
output reg [6:0] SSD0   */

output reg [2:0] X_COORD,
output reg [2:0] Y_COORD

);

reg turn;
reg [1:0] timer, dirY, scoreA, scoreB;
reg [3:0] state;

//states: 
//general
parameter IDLE = 4'b0000, DISP = 4'b0001, END_STATE = 4'b1010;
//turn A
parameter HIT_A = 4'b0010, SEND_B = 4'b0011, RESP_B = 4'b0100, GOAL_A = 4'b0101;
// //turn B
parameter HIT_B = 4'b0110, SEND_A = 4'b0111, RESP_A = 4'b1000, GOAL_B = 4'b1001;

always @(posedge clk or posedge rst)
begin
//your code goes here
    if(rst)
    begin
        state <= IDLE;
        turn <= 0;
        dirY <= 0;
        scoreA <= 0;
        scoreB <= 0;
        timer <= 0;
        X_COORD <= 0;
        Y_COORD <= 0;
    end
    else
    begin
        case(state)
            IDLE:
            begin
                if(BTN_A==1 && BTN_B==0)
                begin
                    state <= DISP;
                    turn <= 0;
                end
                else if(BTN_A==0 && BTN_B==1)
                begin
                    state <= DISP;
                    turn <= 1;
                end
                else
                begin
                    state <= IDLE;
                end
            end
            DISP:
            begin
                if(timer < 2)
                begin
                    state <= DISP;
                    timer <= timer + 1;
                end
                else
                begin
                    if (turn == 1)
                    begin
                        state <= HIT_B;
                    end
                    else
                    begin
                        state <= HIT_A;
                    end
                    timer <= 0;
                end
            end
            HIT_A:
            begin
                if (BTN_A && Y_in_A < 5)
                begin
                    state <= SEND_B;
                    X_COORD <= 0;
                    Y_COORD <= Y_in_A;
                    dirY <= DIR_A;
                end
                else
                begin
                    state <= HIT_A;
                end
            end
            HIT_B:
            begin
                if (BTN_B && Y_in_B < 5)
                begin
                    state <= SEND_A;
                    X_COORD <= 4;
                    Y_COORD <= Y_in_B;
                    dirY <= DIR_B;
                end
                else
                begin
                    state <= HIT_B;
                end
            end
            SEND_A:
            begin
                if (timer < 2)          //spend two seconds for every puck move
                begin
                    state <= SEND_A;
                    timer <= timer + 1;
                end
                else
                begin
                    timer <= 0;
                    if (dirY == 2'b10)
                    begin
                        if (Y_COORD == 0)
                        begin
                            dirY <= 2'b01;
                            Y_COORD <= Y_COORD + 1;
                        end
                        else
                        begin
                            Y_COORD <= Y_COORD - 1;
                        end
                    end
                    else if (dirY == 2'b01)
                    begin
                        if (Y_COORD == 4)
                        begin
                            dirY <= 2'b10;
                            Y_COORD <= Y_COORD - 1;
                        end
                        else
                        begin
                            Y_COORD <= Y_COORD + 1;
                        end
                    end
                    else
                    //when dirY == 2'b00 or in error case of 2'b11, direction sets to 0
                    begin
                        Y_COORD <= Y_COORD;
                        dirY <= 2'b00;
                    end
                    if (X_COORD > 1)
                    begin
                        state <= SEND_A;
                        X_COORD <= X_COORD - 1;
                    end
                    else
                    begin
                        X_COORD <= 0;
                        state <= RESP_A;
                    end
                end
            end
            SEND_B:
            begin
                if (timer < 2)          //spend two seconds for every puck move
                begin
                    state <= SEND_B;
                    timer <= timer + 1;
                end
                else
                begin
                    timer <= 0;
                    if (dirY == 2'b10)
                    begin
                        if (Y_COORD == 0)
                        begin
                            dirY <= 2'b01;
                            Y_COORD <= Y_COORD + 1;
                        end
                        else
                        begin
                            Y_COORD <= Y_COORD - 1;
                        end
                    end
                    else if (dirY == 2'b01)
                    begin
                        if (Y_COORD == 4)
                        begin
                            dirY <= 2'b10;
                            Y_COORD <= Y_COORD - 1;
                        end
                        else
                        begin
                            Y_COORD <= Y_COORD + 1;
                        end
                    end
                    else
                    //when dirY == 2'b00 or in error case of 2'b11, direction sets to 0
                    begin
                        Y_COORD <= Y_COORD;
                        dirY <= 2'b00;
                    end
                    if (X_COORD < 3)
                    begin
                        state <= SEND_B;
                        X_COORD <= X_COORD + 1;
                    end
                    else
                    begin
                        X_COORD <= 4;
                        state <= RESP_B;
                    end
                end
            end
            RESP_A:
            begin
                if(timer < 2)
                begin
                    if (BTN_A && Y_COORD == Y_in_A)
                    begin
                        X_COORD <= 1;
                        timer <= 0;
                        if (DIR_B == 2'b10)
                        begin
                            if (Y_COORD == 0)
                            begin
                                dirY <= 2'b01;
                                Y_COORD <= Y_COORD + 1;                                        
                            end
                            else
                            begin
                                dirY <= DIR_A;
                                Y_COORD <= Y_COORD - 1;
                            end
                        end
                        else if (DIR_B == 2'b01)
                        begin
                            if (Y_COORD == 4)
                            begin
                                dirY <= 2'b10;
                                Y_COORD <= Y_COORD - 1;
                            end
                            else
                            begin
                                dirY <= DIR_A;
                                Y_COORD <= Y_COORD + 1;
                            end
                        end
                        else
                        //when DIR_B == 2'b00 or in error case of 2'b11, direction sets to 0
                        begin
                            Y_COORD <= Y_COORD;
                            dirY <= 2'b00;
                        end
                        state <= SEND_B;
                    end
                    else
                    begin
                        state <= RESP_A;
                        timer <= timer + 1;
                    end

                end
                else
                begin
                    state <= GOAL_B;
                    scoreB <= scoreB + 1;
                    timer <= 0;
                end
            end
            RESP_B:
            begin
                if(timer < 2)
                begin
                    if (BTN_B && Y_COORD == Y_in_B)
                    begin
                        X_COORD <= 3;
                        timer <= 0;
                        if (DIR_A == 2'b10)
                        begin
                            if (Y_COORD == 0)
                            begin
                                dirY <= 2'b01;
                                Y_COORD <= Y_COORD + 1;                                        
                            end
                            else
                            begin
                                dirY <= DIR_B;
                                Y_COORD <= Y_COORD - 1;
                            end
                        end
                        else if (DIR_A == 2'b01)
                        begin
                            if (Y_COORD == 4)
                            begin
                                dirY <= 2'b10;
                                Y_COORD <= Y_COORD - 1;
                            end
                            else
                            begin
                                dirY <= DIR_B;
                                Y_COORD <= Y_COORD + 1;
                            end
                        end
                        else
                        //when DIR_A == 2'b00 or in error case of 2'b11, direction sets to 0
                        begin
                            Y_COORD <= Y_COORD;
                            dirY <= 2'b00;
                        end
                        state <= SEND_A;
                    end
                    else
                    begin
                        state <= RESP_B;
                        timer <= timer + 1;
                    end
                end
                else
                begin
                    state <= GOAL_A;
                    scoreA <= scoreA + 1;
                    timer <= 0;
                end
            end
            GOAL_A:
            begin
                if(timer < 2)
                begin
                    state <= GOAL_A;
                    timer <= timer + 1;
                end
                else
                begin
                    timer <= 0;
                    if (scoreA == 3)
                    begin
                        turn <= 0;
                        state <= END_STATE;
                    end
                    else
                    begin
                        state <= HIT_B;
                    end 
                end
            end
            GOAL_B:
            begin
                if(timer < 2)
                begin
                    state <= GOAL_B;
                    timer <= timer + 1;
                end
                else
                begin
                    timer <= 0;
                    if (scoreB == 3)
                    begin
                        turn <= 1;
                        state <= END_STATE;
                    end
                    else
                    begin
                        state <= HIT_A;
                    end 
                end
            end
            END_STATE:
            begin
                state <= END_STATE;
            end
            default:
            begin
                state <= IDLE;
                turn <= 0;
                dirY <= 0;
                timer <= 0;
            end
        endcase
    end
end
 
endmodule

 
// endmodule

hockey_tb.v
module hockey_tb();


parameter HP = 5;       // Half period of our clock signal
parameter FP = (2*HP);  // Full period of our clock signal

reg clk, rst, BTN_A, BTN_B;
reg [1:0] DIR_A;
reg [1:0] DIR_B;
reg [2:0] Y_in_A;
reg [2:0] Y_in_B;

wire [2:0] X_COORD, Y_COORD;

// Our design-under-test is the DigiHockey module
hockey dut(clk, rst, BTN_A, BTN_B, DIR_A, DIR_B, Y_in_A, Y_in_B, X_COORD,Y_COORD);

// This always statement automatically cycles between clock high and clock low in HP (Half Period) time. Makes writing test-benches easier.
always #HP clk = ~clk;

initial begin
	$dumpfile("hockey.vcd"); //  * Our waveform is saved under this file.
    $dumpvars(0,hockey_tb); // * Get the variables from the module.
    
    $display("Simulation started.");
    
    clk = 0; 
    rst = 0;
    BTN_A = 0;
	BTN_B = 0;
	DIR_A = 0;
	DIR_B = 0;
    Y_in_A = 0;
    Y_in_B = 0;
    
	#FP;
	rst=1;
	#FP;
	rst=0;
	
	// Here, you are asked to write your test scenario.
	BTN_A = 1'b1;
	#10;
	BTN_A = 1'b0;
	#30;
	BTN_A = 1'b1;
	Y_in_A = 3'b010;
	DIR_A = 2'b00;
	#10;
	BTN_A = 1'b0;
	#120;						//puck movement time
	BTN_B = 1'b1;
	Y_in_B = 3'b011;		//not equal to Y_COORD, should be goal for A
	#20;
	BTN_B = 1'b0;
	#40;

	BTN_B = 1'b1;
	Y_in_B = 3'b010;
	DIR_B = 2'b00;
	#10;
	BTN_B = 1'b0;
	#120;
	BTN_A = 1'b1;
	Y_in_A = 3'b010;		// equal to Y_COORD
	#10;
	BTN_A = 1'b0;
	#90;					//puck movement time
	BTN_B = 1'b1;
	Y_in_B = 3'b010;
	DIR_B = 2'b00;
	#10;
	BTN_B = 1'b0;
	#90;
	BTN_A = 1'b1;
	Y_in_A = 3'b000;
	#20;
	BTN_A = 1'b0;
	#40;

	BTN_A = 1'b1;
	Y_in_A = 3'b010;
	DIR_A = 2'b00;
	#10;
	BTN_A = 1'b0;
	#120;
	BTN_B = 1'b1;
	Y_in_B = 3'b000;
	#20;
	BTN_B = 1'b0;
	#40;

	BTN_B = 1'b1;
	Y_in_B = 3'b010;
	DIR_B = 2'b00;
	#10;
	BTN_B = 1'b0;
	#120;
	BTN_A = 1'b1;
	Y_in_A = 3'b010;		// equal to Y_COORD
	#10;
	BTN_A = 1'b0;
	#90;					//puck movement time
	BTN_B = 1'b1;
	Y_in_B = 3'b010;
	//DIR_B = 2'b00;
	#10;
	BTN_B = 1'b0;
	#90;
	BTN_A = 1'b1;
	Y_in_A = 3'b010;		// equal to Y_COORD
	#10;
	BTN_A = 1'b0;
	#90;					//puck movement time
	BTN_B = 1'b1;
	Y_in_B = 3'b000;
	#20;
	BTN_B = 1'b0;
	#40;
	#100;
	
    $display("Simulation finished.");
    $finish(); // Finish simulation.

end



endmodule

hockey.vcd
$date
	Tue Jan 02 15:29:06 2024
$end
$version
	Icarus Verilog
$end
$timescale
	1s
$end
$scope module hockey_tb $end
$var wire 3 ! Y_COORD [2:0] $end
$var wire 3 " X_COORD [2:0] $end
$var parameter 64 # FP $end
$var parameter 32 $ HP $end
$var reg 1 % BTN_A $end
$var reg 1 & BTN_B $end
$var reg 2 ' DIR_A [1:0] $end
$var reg 2 ( DIR_B [1:0] $end
$var reg 3 ) Y_in_A [2:0] $end
$var reg 3 * Y_in_B [2:0] $end
$var reg 1 + clk $end
$var reg 1 , rst $end
$scope module dut $end
$var wire 1 % BTN_A $end
$var wire 1 & BTN_B $end
$var wire 2 - DIR_A [1:0] $end
$var wire 2 . DIR_B [1:0] $end
$var wire 3 / Y_in_A [2:0] $end
$var wire 3 0 Y_in_B [2:0] $end
$var wire 1 + clk $end
$var wire 1 , rst $end
$var parameter 4 1 DISP $end
$var parameter 4 2 END_STATE $end
$var parameter 4 3 GOAL_A $end
$var parameter 4 4 GOAL_B $end
$var parameter 4 5 HIT_A $end
$var parameter 4 6 HIT_B $end
$var parameter 4 7 IDLE $end
$var parameter 4 8 RESP_A $end
$var parameter 4 9 RESP_B $end
$var parameter 4 : SEND_A $end
$var parameter 4 ; SEND_B $end
$var reg 3 < X_COORD [2:0] $end
$var reg 3 = Y_COORD [2:0] $end
$var reg 2 > dirY [1:0] $end
$var reg 2 ? scoreA [1:0] $end
$var reg 2 @ scoreB [1:0] $end
$var reg 4 A state [3:0] $end
$var reg 2 B timer [1:0] $end
$var reg 1 C turn $end
$upscope $end
$upscope $end
$enddefinitions $end
$comment Show the parameter values. $end
$dumpall
b11 ;
b111 :
b100 9
b1000 8
b0 7
b110 6
b10 5
b1001 4
b101 3
b1010 2
b1 1
b101 $
b1010 #
$end
#0
$dumpvars
xC
bx B
bx A
bx @
bx ?
bx >
bx =
bx <
b0 0
b0 /
b0 .
b0 -
0,
0+
b0 *
b0 )
b0 (
b0 '
0&
0%
bx "
bx !
$end
#5
b0 B
b0 >
0C
b0 A
1+
#10
b0 !
b0 =
b0 "
b0 <
b0 @
b0 ?
0+
1,
#15
1+
#20
0+
1%
0,
#25
b1 A
1+
#30
0+
0%
#35
b1 B
1+
#40
0+
#45
b10 B
1+
#50
0+
#55
b0 B
b10 A
1+
#60
0+
b10 )
b10 /
1%
#65
b10 !
b10 =
b11 A
1+
#70
0+
0%
#75
b1 B
1+
#80
0+
#85
b10 B
1+
#90
0+
#95
b1 "
b1 <
b0 B
1+
#100
0+
#105
b1 B
1+
#110
0+
#115
b10 B
1+
#120
0+
#125
b10 "
b10 <
b0 B
1+
#130
0+
#135
b1 B
1+
#140
0+
#145
b10 B
1+
#150
0+
#155
b11 "
b11 <
b0 B
1+
#160
0+
#165
b1 B
1+
#170
0+
#175
b10 B
1+
#180
0+
#185
b100 A
b100 "
b100 <
b0 B
1+
#190
0+
b11 *
b11 0
1&
#195
b1 B
1+
#200
0+
#205
b10 B
1+
#210
0+
0&
#215
b0 B
b1 ?
b101 A
1+
#220
0+
#225
b1 B
1+
#230
0+
#235
b10 B
1+
#240
0+
#245
b110 A
b0 B
1+
#250
0+
b10 *
b10 0
1&
#255
b111 A
1+
#260
0+
0&
#265
b1 B
1+
#270
0+
#275
b10 B
1+
#280
0+
#285
b11 "
b11 <
b0 B
1+
#290
0+
#295
b1 B
1+
#300
0+
#305
b10 B
1+
#310
0+
#315
b10 "
b10 <
b0 B
1+
#320
0+
#325
b1 B
1+
#330
0+
#335
b10 B
1+
#340
0+
#345
b1 "
b1 <
b0 B
1+
#350
0+
#355
b1 B
1+
#360
0+
#365
b10 B
1+
#370
0+
#375
b1000 A
b0 "
b0 <
b0 B
1+
#380
0+
1%
#385
b11 A
b1 "
b1 <
1+
#390
0+
0%
#395
b1 B
1+
#400
0+
#405
b10 B
1+
#410
0+
#415
b10 "
b10 <
b0 B
1+
#420
0+
#425
b1 B
1+
#430
0+
#435
b10 B
1+
#440
0+
#445
b11 "
b11 <
b0 B
1+
#450
0+
#455
b1 B
1+
#460
0+
#465
b10 B
1+
#470
0+
#475
b100 A
b100 "
b100 <
b0 B
1+
#480
0+
1&
#485
b111 A
b11 "
b11 <
1+
#490
0+
0&
#495
b1 B
1+
#500
0+
#505
b10 B
1+
#510
0+
#515
b10 "
b10 <
b0 B
1+
#520
0+
#525
b1 B
1+
#530
0+
#535
b10 B
1+
#540
0+
#545
b1 "
b1 <
b0 B
1+
#550
0+
#555
b1 B
1+
#560
0+
#565
b10 B
1+
#570
0+
#575
b1000 A
b0 "
b0 <
b0 B
1+
#580
0+
b0 )
b0 /
1%
#585
b1 B
1+
#590
0+
#595
b10 B
1+
#600
0+
0%
#605
b0 B
b1 @
b1001 A
1+
#610
0+
#615
b1 B
1+
#620
0+
#625
b10 B
1+
#630
0+
#635
b10 A
b0 B
1+
#640
0+
b10 )
b10 /
1%
#645
b11 A
1+
#650
0+
0%
#655
b1 B
1+
#660
0+
#665
b10 B
1+
#670
0+
#675
b1 "
b1 <
b0 B
1+
#680
0+
#685
b1 B
1+
#690
0+
#695
b10 B
1+
#700
0+
#705
b10 "
b10 <
b0 B
1+
#710
0+
#715
b1 B
1+
#720
0+
#725
b10 B
1+
#730
0+
#735
b11 "
b11 <
b0 B
1+
#740
0+
#745
b1 B
1+
#750
0+
#755
b10 B
1+
#760
0+
#765
b100 A
b100 "
b100 <
b0 B
1+
#770
0+
b0 *
b0 0
1&
#775
b1 B
1+
#780
0+
#785
b10 B
1+
#790
0+
0&
#795
b0 B
b10 ?
b101 A
1+
#800
0+
#805
b1 B
1+
#810
0+
#815
b10 B
1+
#820
0+
#825
b110 A
b0 B
1+
#830
0+
b10 *
b10 0
1&
#835
b111 A
1+
#840
0+
0&
#845
b1 B
1+
#850
0+
#855
b10 B
1+
#860
0+
#865
b11 "
b11 <
b0 B
1+
#870
0+
#875
b1 B
1+
#880
0+
#885
b10 B
1+
#890
0+
#895
b10 "
b10 <
b0 B
1+
#900
0+
#905
b1 B
1+
#910
0+
#915
b10 B
1+
#920
0+
#925
b1 "
b1 <
b0 B
1+
#930
0+
#935
b1 B
1+
#940
0+
#945
b10 B
1+
#950
0+
#955
b1000 A
b0 "
b0 <
b0 B
1+
#960
0+
1%
#965
b11 A
b1 "
b1 <
1+
#970
0+
0%
#975
b1 B
1+
#980
0+
#985
b10 B
1+
#990
0+
#995
b10 "
b10 <
b0 B
1+
#1000
0+
#1005
b1 B
1+
#1010
0+
#1015
b10 B
1+
#1020
0+
#1025
b11 "
b11 <
b0 B
1+
#1030
0+
#1035
b1 B
1+
#1040
0+
#1045
b10 B
1+
#1050
0+
#1055
b100 A
b100 "
b100 <
b0 B
1+
#1060
0+
1&
#1065
b111 A
b11 "
b11 <
1+
#1070
0+
0&
#1075
b1 B
1+
#1080
0+
#1085
b10 B
1+
#1090
0+
#1095
b10 "
b10 <
b0 B
1+
#1100
0+
#1105
b1 B
1+
#1110
0+
#1115
b10 B
1+
#1120
0+
#1125
b1 "
b1 <
b0 B
1+
#1130
0+
#1135
b1 B
1+
#1140
0+
#1145
b10 B
1+
#1150
0+
#1155
b1000 A
b0 "
b0 <
b0 B
1+
#1160
0+
1%
#1165
b11 A
b1 "
b1 <
1+
#1170
0+
0%
#1175
b1 B
1+
#1180
0+
#1185
b10 B
1+
#1190
0+
#1195
b10 "
b10 <
b0 B
1+
#1200
0+
#1205
b1 B
1+
#1210
0+
#1215
b10 B
1+
#1220
0+
#1225
b11 "
b11 <
b0 B
1+
#1230
0+
#1235
b1 B
1+
#1240
0+
#1245
b10 B
1+
#1250
0+
#1255
b100 A
b100 "
b100 <
b0 B
1+
#1260
0+
b0 *
b0 0
1&
#1265
b1 B
1+
#1270
0+
#1275
b10 B
1+
#1280
0+
0&
#1285
b0 B
b11 ?
b101 A
1+
#1290
0+
#1295
b1 B
1+
#1300
0+
#1305
b10 B
1+
#1310
0+
#1315
b1010 A
b0 B
1+
